nbs/bluetopo/__init__.py
nbs/bluetopo/cli/cli.py
nbs/bluetopo/core/build_vrt.py
nbs/bluetopo/core/fetch_tiles.py
BlueTopo-0.7.0.dist-info/LICENSE
BlueTopo-0.7.0.dist-info/METADATA
BlueTopo-0.7.0.dist-info/WHEEL
BlueTopo-0.7.0.dist-info/entry_points.txt
BlueTopo-0.7.0.dist-info/top_level.txt
BlueTopo-0.7.0.dist-info/RECORD
