Metadata-Version: 2.1
Name: BlueTopo
Version: 0.7.0
Summary: National Bathymetric Source Project BlueTopo
Author-email: Glen Rice <ocs.nbs@noaa.gov>, Tashi Geleg <ocs.nbs@noaa.gov>
License: CC0 1.0 Universal
Project-URL: homepage, https://www.nauticalcharts.noaa.gov/data/bluetopo.html
Project-URL: source, https://github.com/noaa-ocs-hydrography/BlueTopo
Keywords: BlueTopo,National Bathymetric Source,Bathymetry
License-File: LICENSE
Requires-Dist: numpy
Requires-Dist: boto3
Requires-Dist: tqdm
